README.md
setup.py
SBLPy.egg-info/PKG-INFO
SBLPy.egg-info/SOURCES.txt
SBLPy.egg-info/dependency_links.txt
SBLPy.egg-info/top_level.txt
sblpy/__init__.py
sblpy/__main__.py
sblpy/core.py
sblpy/errors.py
sblpy/revised.py