Metadata-Version: 2.1
Name: SBLPy
Version: 1.0.0
Summary: SBLP's HTTP system, wrapped into python
Home-page: https://github.com/EEKIM10/sblpy
Author: EEKIM10
Author-email: eek@clicksminuteper.net
License: MIT
Platform: UNKNOWN
